FlutterFinder-1.0.1.data/data/share/man/man1/flutter_finder.1
flutter_finder/__init__.py
flutter_finder/__main__.py
flutter_finder/flutter_finder.py
flutter_finder/main.py
flutter_finder/utils.py
FlutterFinder-1.0.1.dist-info/LICENSE
FlutterFinder-1.0.1.dist-info/METADATA
FlutterFinder-1.0.1.dist-info/WHEEL
FlutterFinder-1.0.1.dist-info/entry_points.txt
FlutterFinder-1.0.1.dist-info/top_level.txt
FlutterFinder-1.0.1.dist-info/RECORD
