Metadata-Version: 2.1
Name: FlutterFinder
Version: 1.0.1
Summary: A command-line interface (CLI) tool to find Flutter apps in a directory.
Home-page: https://github.com/chan27-2/flutter-finder
Author: Sai Chandan Kadarla
Author-email: chandankadarla2722002@gmail.com
Classifier: Development Status :: 5 - Production/Stable
Classifier: Intended Audience :: Developers
Classifier: License :: OSI Approved :: MIT License
Classifier: Natural Language :: English
Classifier: Programming Language :: Python :: 3.7
Classifier: Topic :: Utilities
Requires-Python: >=3.7
License-File: LICENSE
